LICENSE
README.md
setup.py
designmate.egg-info/PKG-INFO
designmate.egg-info/SOURCES.txt
designmate.egg-info/dependency_links.txt
designmate.egg-info/top_level.txt
designmate/flask/__init__.py
designmate/flask/flask.py
designmate/utils/__init__.py
designmate/utils/utils.py