Metadata-Version: 2.1
Name: designmate
Version: 1.0.0
Summary: DesignMate é uma biblioteca Python que facilita o desenvolvimento de robôs de automação web com Selenium e a criação de projetos Flask seguindo padrões de projeto. Com funções utilitárias e templates prontos, o DesignMate ajuda desenvolvedores a acelerar a criação de automações robustas e APIs Flask bem estruturadas. Ideal para quem busca produtividade e boas práticas em automação e desenvolvimento web.
Home-page: https://github.com/gabriellopesdesouza2002/DesignMate
Author: Gabriel Lopes de Souza
Author-email: gabriellopesdesouza2002@gmail.com
License: MIT License
Keywords: selenium,automation,web-automation,robots,flask,web-development,python,automation-tools,web-scraping,testing,browser-automation,selenium-webdriver,selenium-framework,python-automation,web-robots,automation-scripts,selenium-utils,flask-templates,flask-automation,python-tools
License-File: LICENSE
